setup.py
veryfay/__init__.py
veryfay/activity.py
veryfay/activity_authorization.py
veryfay/activity_registry.py
veryfay/authorization_engine.py
veryfay/authorization_exception.py
veryfay/permission_set.py
veryfay/permission_verifier.py
veryfay/role_set.py
veryfay.egg-info/PKG-INFO
veryfay.egg-info/SOURCES.txt
veryfay.egg-info/dependency_links.txt
veryfay.egg-info/not-zip-safe
veryfay.egg-info/top_level.txt