Metadata-Version: 1.1
Name: veryfay
Version: 0.1.0
Summary: Activity based authorization.
Home-page: https://github.com/florinn/veryfay-python
Author: Florin Nitoi
Author-email: florin.nitoi@gmail.com
License: MIT
Keywords: authorization,engine,activity,role,permission
Platform: UNKNOWN
Classifier: Development Status :: 5 - Production/Stable
Classifier: Intended Audience :: Developers
Classifier: Topic :: Software Development :: Libraries :: Python Modules
Classifier: License :: OSI Approved :: MIT License
Classifier: Programming Language :: Python :: 3.3
Classifier: Programming Language :: Python :: 3.4
Classifier: Programming Language :: Python :: 3.5
